[
  {
    "id": 0,
    "name": "Nash's Lingoage",
    "price": "$286.97",
    "tags": [
      {
        "id": 0,
        "tag": "Gwen"
      },
      {
        "id": 1,
        "tag": "Marci"
      },
      {
        "id": 2,
        "tag": "Humphrey"
      }
    ]
  },
  {
    "id": 1,
    "name": "Leonard's Isbol",
    "price": "$161.45",
    "tags": [
      {
        "id": 0,
        "tag": "Gill"
      },
      {
        "id": 1,
        "tag": "Mayer"
      }
    ]
  },
  {
    "id": 2,
    "name": "Hunt's Fibrodyne",
    "price": "$105.62",
    "tags": [
      {
        "id": 0,
        "tag": "Candice"
      },
      {
        "id": 1,
        "tag": "Francis"
      },
      {
        "id": 2,
        "tag": "Oneill"
      },
      {
        "id": 3,
        "tag": "Meyer"
      },
      {
        "id": 4,
        "tag": "Elaine"
      },
      {
        "id": 5,
        "tag": "Harrell"
      },
      {
        "id": 6,
        "tag": "Whitney"
      },
      {
        "id": 7,
        "tag": "Neva"
      }
    ]
  },
  {
    "id": 3,
    "name": "Byers's Gracker",
    "price": "$109.46",
    "tags": [
      {
        "id": 0,
        "tag": "Lucille"
      },
      {
        "id": 1,
        "tag": "Bobbie"
      },
      {
        "id": 2,
        "tag": "Giles"
      },
      {
        "id": 3,
        "tag": "Corina"
      },
      {
        "id": 4,
        "tag": "Maggie"
      },
      {
        "id": 5,
        "tag": "Nicole"
      },
      {
        "id": 6,
        "tag": "Hensley"
      },
      {
        "id": 7,
        "tag": "Pennington"
      },
      {
        "id": 8,
        "tag": "Aimee"
      },
      {
        "id": 9,
        "tag": "Ollie"
      },
      {
        "id": 10,
        "tag": "Amelia"
      }
    ]
  },
  {
    "id": 4,
    "name": "Hardy's Geekfarm",
    "price": "$174.36",
    "tags": [
      {
        "id": 0,
        "tag": "Pugh"
      },
      {
        "id": 1,
        "tag": "Pierce"
      },
      {
        "id": 2,
        "tag": "Juliana"
      },
      {
        "id": 3,
        "tag": "Macias"
      },
      {
        "id": 4,
        "tag": "Nannie"
      },
      {
        "id": 5,
        "tag": "Colon"
      }
    ]
  },
  {
    "id": 5,
    "name": "Gilbert's Xymonk",
    "price": "$264.5",
    "tags": [
      {
        "id": 0,
        "tag": "Ford"
      },
      {
        "id": 1,
        "tag": "Mona"
      },
      {
        "id": 2,
        "tag": "Walter"
      },
      {
        "id": 3,
        "tag": "Melisa"
      },
      {
        "id": 4,
        "tag": "Tanner"
      },
      {
        "id": 5,
        "tag": "King"
      },
      {
        "id": 6,
        "tag": "Bernadette"
      },
      {
        "id": 7,
        "tag": "Rosa"
      },
      {
        "id": 8,
        "tag": "Lakisha"
      },
      {
        "id": 9,
        "tag": "Dorsey"
      },
      {
        "id": 10,
        "tag": "Wendi"
      }
    ]
  },
  {
    "id": 6,
    "name": "Mccoy's Tingles",
    "price": "$353.42",
    "tags": [
      {
        "id": 0,
        "tag": "Ashlee"
      },
      {
        "id": 1,
        "tag": "Carrie"
      },
      {
        "id": 2,
        "tag": "Hudson"
      },
      {
        "id": 3,
        "tag": "Mckee"
      },
      {
        "id": 4,
        "tag": "Odessa"
      },
      {
        "id": 5,
        "tag": "Corrine"
      },
      {
        "id": 6,
        "tag": "Duran"
      },
      {
        "id": 7,
        "tag": "Holmes"
      },
      {
        "id": 8,
        "tag": "Roxie"
      },
      {
        "id": 9,
        "tag": "Figueroa"
      },
      {
        "id": 10,
        "tag": "Brittney"
      },
      {
        "id": 11,
        "tag": "Britney"
      }
    ]
  },
  {
    "id": 7,
    "name": "Daugherty's Earthplex",
    "price": "$179.19",
    "tags": [
      {
        "id": 0,
        "tag": "Vang"
      },
      {
        "id": 1,
        "tag": "Paul"
      },
      {
        "id": 2,
        "tag": "Rhonda"
      },
      {
        "id": 3,
        "tag": "Michael"
      },
      {
        "id": 4,
        "tag": "Kayla"
      },
      {
        "id": 5,
        "tag": "Padilla"
      },
      {
        "id": 6,
        "tag": "Gentry"
      },
      {
        "id": 7,
        "tag": "Myrna"
      },
      {
        "id": 8,
        "tag": "Olive"
      },
      {
        "id": 9,
        "tag": "Hays"
      }
    ]
  },
  {
    "id": 8,
    "name": "Graham's Cormoran",
    "price": "$318.71",
    "tags": [
      {
        "id": 0,
        "tag": "Dodson"
      },
      {
        "id": 1,
        "tag": "Sherry"
      },
      {
        "id": 2,
        "tag": "Vanessa"
      },
      {
        "id": 3,
        "tag": "Reva"
      },
      {
        "id": 4,
        "tag": "Rosa"
      }
    ]
  },
  {
    "id": 9,
    "name": "Leon's Overfork",
    "price": "$393.38",
    "tags": [
      {
        "id": 0,
        "tag": "Sheena"
      },
      {
        "id": 1,
        "tag": "Lane"
      },
      {
        "id": 2,
        "tag": "Shannon"
      },
      {
        "id": 3,
        "tag": "Colette"
      }
    ]
  },
  {
    "id": 10,
    "name": "Brooks's Immunics",
    "price": "$189.97",
    "tags": [
      {
        "id": 0,
        "tag": "Dianne"
      },
      {
        "id": 1,
        "tag": "Kelsey"
      },
      {
        "id": 2,
        "tag": "Watts"
      },
      {
        "id": 3,
        "tag": "Reba"
      },
      {
        "id": 4,
        "tag": "Claudia"
      },
      {
        "id": 5,
        "tag": "Wilcox"
      },
      {
        "id": 6,
        "tag": "Ruth"
      },
      {
        "id": 7,
        "tag": "Huff"
      },
      {
        "id": 8,
        "tag": "Anderson"
      },
      {
        "id": 9,
        "tag": "Snow"
      },
      {
        "id": 10,
        "tag": "Burch"
      },
      {
        "id": 11,
        "tag": "Vincent"
      }
    ]
  },
  {
    "id": 11,
    "name": "Dawson's Zillar",
    "price": "$177.99",
    "tags": [
      {
        "id": 0,
        "tag": "Logan"
      },
      {
        "id": 1,
        "tag": "Perkins"
      },
      {
        "id": 2,
        "tag": "Kate"
      }
    ]
  },
  {
    "id": 12,
    "name": "Kelley's Twiist",
    "price": "$32.52",
    "tags": [
      {
        "id": 0,
        "tag": "Aurelia"
      },
      {
        "id": 1,
        "tag": "Casey"
      }
    ]
  },
  {
    "id": 13,
    "name": "Black's Geekol",
    "price": "$280.08",
    "tags": [
      {
        "id": 0,
        "tag": "Julia"
      },
      {
        "id": 1,
        "tag": "Nichole"
      },
      {
        "id": 2,
        "tag": "Ochoa"
      }
    ]
  },
  {
    "id": 14,
    "name": "Bolton's Lexicondo",
    "price": "$292.18",
    "tags": [
      {
        "id": 0,
        "tag": "Latisha"
      },
      {
        "id": 1,
        "tag": "Taylor"
      },
      {
        "id": 2,
        "tag": "Luella"
      },
      {
        "id": 3,
        "tag": "Magdalena"
      },
      {
        "id": 4,
        "tag": "Blankenship"
      },
      {
        "id": 5,
        "tag": "Aisha"
      }
    ]
  },
  {
    "id": 15,
    "name": "Cabrera's Snorus",
    "price": "$254.45",
    "tags": [
      {
        "id": 0,
        "tag": "Lara"
      },
      {
        "id": 1,
        "tag": "Harrington"
      },
      {
        "id": 2,
        "tag": "Melton"
      },
      {
        "id": 3,
        "tag": "Carrillo"
      }
    ]
  },
  {
    "id": 16,
    "name": "Dyer's Eclipto",
    "price": "$399.36",
    "tags": [
      {
        "id": 0,
        "tag": "Perry"
      },
      {
        "id": 1,
        "tag": "Ericka"
      },
      {
        "id": 2,
        "tag": "Angelique"
      },
      {
        "id": 3,
        "tag": "Sharron"
      },
      {
        "id": 4,
        "tag": "Riggs"
      },
      {
        "id": 5,
        "tag": "Mable"
      },
      {
        "id": 6,
        "tag": "Knox"
      },
      {
        "id": 7,
        "tag": "Carlene"
      },
      {
        "id": 8,
        "tag": "Irwin"
      },
      {
        "id": 9,
        "tag": "Sherrie"
      },
      {
        "id": 10,
        "tag": "Patel"
      },
      {
        "id": 11,
        "tag": "Billie"
      }
    ]
  },
  {
    "id": 17,
    "name": "Holman's Digifad",
    "price": "$239.05",
    "tags": [
      {
        "id": 0,
        "tag": "Nelda"
      },
      {
        "id": 1,
        "tag": "Clayton"
      }
    ]
  },
  {
    "id": 18,
    "name": "Bray's Intergeek",
    "price": "$209.64",
    "tags": [
      {
        "id": 0,
        "tag": "Esmeralda"
      },
      {
        "id": 1,
        "tag": "Sheri"
      },
      {
        "id": 2,
        "tag": "Keller"
      },
      {
        "id": 3,
        "tag": "Earline"
      },
      {
        "id": 4,
        "tag": "Lidia"
      },
      {
        "id": 5,
        "tag": "Rosario"
      },
      {
        "id": 6,
        "tag": "Mccullough"
      },
      {
        "id": 7,
        "tag": "Day"
      }
    ]
  },
  {
    "id": 19,
    "name": "Larson's Bleeko",
    "price": "$90.4",
    "tags": [
      {
        "id": 0,
        "tag": "Ware"
      },
      {
        "id": 1,
        "tag": "Alfreda"
      },
      {
        "id": 2,
        "tag": "Reid"
      },
      {
        "id": 3,
        "tag": "Spencer"
      },
      {
        "id": 4,
        "tag": "Hood"
      },
      {
        "id": 5,
        "tag": "Dunlap"
      },
      {
        "id": 6,
        "tag": "Brewer"
      },
      {
        "id": 7,
        "tag": "Buckner"
      },
      {
        "id": 8,
        "tag": "Latasha"
      },
      {
        "id": 9,
        "tag": "Ayers"
      },
      {
        "id": 10,
        "tag": "Clare"
      },
      {
        "id": 11,
        "tag": "Henrietta"
      }
    ]
  },
  {
    "id": 20,
    "name": "Franklin's Navir",
    "price": "$154.44",
    "tags": [
      {
        "id": 0,
        "tag": "Mercer"
      },
      {
        "id": 1,
        "tag": "Sadie"
      },
      {
        "id": 2,
        "tag": "Lowe"
      },
      {
        "id": 3,
        "tag": "Grant"
      },
      {
        "id": 4,
        "tag": "Thompson"
      },
      {
        "id": 5,
        "tag": "Castillo"
      },
      {
        "id": 6,
        "tag": "Preston"
      },
      {
        "id": 7,
        "tag": "Freida"
      },
      {
        "id": 8,
        "tag": "Rosalinda"
      },
      {
        "id": 9,
        "tag": "Hutchinson"
      }
    ]
  },
  {
    "id": 21,
    "name": "Hebert's Melbacor",
    "price": "$348.74",
    "tags": [
      {
        "id": 0,
        "tag": "Melendez"
      },
      {
        "id": 1,
        "tag": "Ortega"
      },
      {
        "id": 2,
        "tag": "Pratt"
      },
      {
        "id": 3,
        "tag": "Loretta"
      },
      {
        "id": 4,
        "tag": "Ingrid"
      },
      {
        "id": 5,
        "tag": "Roy"
      },
      {
        "id": 6,
        "tag": "Gutierrez"
      },
      {
        "id": 7,
        "tag": "Anne"
      },
      {
        "id": 8,
        "tag": "Caldwell"
      },
      {
        "id": 9,
        "tag": "Tessa"
      }
    ]
  },
  {
    "id": 22,
    "name": "Diaz's Anivet",
    "price": "$135.72",
    "tags": [
      {
        "id": 0,
        "tag": "Ewing"
      },
      {
        "id": 1,
        "tag": "Brittany"
      },
      {
        "id": 2,
        "tag": "Greer"
      },
      {
        "id": 3,
        "tag": "Yesenia"
      },
      {
        "id": 4,
        "tag": "Kara"
      },
      {
        "id": 5,
        "tag": "Irene"
      },
      {
        "id": 6,
        "tag": "Joni"
      },
      {
        "id": 7,
        "tag": "Wheeler"
      }
    ]
  },
  {
    "id": 23,
    "name": "Weber's Dognost",
    "price": "$13.19",
    "tags": [
      {
        "id": 0,
        "tag": "Alice"
      },
      {
        "id": 1,
        "tag": "Viola"
      },
      {
        "id": 2,
        "tag": "Elisabeth"
      },
      {
        "id": 3,
        "tag": "Deborah"
      },
      {
        "id": 4,
        "tag": "Huber"
      }
    ]
  },
  {
    "id": 24,
    "name": "Henson's Jamnation",
    "price": "$377.16",
    "tags": [
      {
        "id": 0,
        "tag": "Michelle"
      },
      {
        "id": 1,
        "tag": "Terry"
      },
      {
        "id": 2,
        "tag": "Barker"
      },
      {
        "id": 3,
        "tag": "Combs"
      },
      {
        "id": 4,
        "tag": "Sandra"
      },
      {
        "id": 5,
        "tag": "Byers"
      },
      {
        "id": 6,
        "tag": "Alejandra"
      },
      {
        "id": 7,
        "tag": "Nancy"
      },
      {
        "id": 8,
        "tag": "Marissa"
      },
      {
        "id": 9,
        "tag": "Murray"
      }
    ]
  },
  {
    "id": 25,
    "name": "Kramer's Turnling",
    "price": "$95.33",
    "tags": [
      {
        "id": 0,
        "tag": "Barry"
      },
      {
        "id": 1,
        "tag": "Toni"
      },
      {
        "id": 2,
        "tag": "Lessie"
      },
      {
        "id": 3,
        "tag": "York"
      },
      {
        "id": 4,
        "tag": "Jacklyn"
      },
      {
        "id": 5,
        "tag": "Lorena"
      },
      {
        "id": 6,
        "tag": "Baird"
      },
      {
        "id": 7,
        "tag": "Helene"
      },
      {
        "id": 8,
        "tag": "Maryann"
      },
      {
        "id": 9,
        "tag": "Warren"
      },
      {
        "id": 10,
        "tag": "Burks"
      },
      {
        "id": 11,
        "tag": "Armstrong"
      }
    ]
  },
  {
    "id": 26,
    "name": "Medina's Mobildata",
    "price": "$16.22",
    "tags": [
      {
        "id": 0,
        "tag": "Holland"
      },
      {
        "id": 1,
        "tag": "Mclaughlin"
      },
      {
        "id": 2,
        "tag": "Alberta"
      },
      {
        "id": 3,
        "tag": "Tina"
      },
      {
        "id": 4,
        "tag": "Jannie"
      },
      {
        "id": 5,
        "tag": "Kaye"
      },
      {
        "id": 6,
        "tag": "Esther"
      },
      {
        "id": 7,
        "tag": "Larson"
      },
      {
        "id": 8,
        "tag": "Douglas"
      },
      {
        "id": 9,
        "tag": "Herring"
      },
      {
        "id": 10,
        "tag": "Hester"
      },
      {
        "id": 11,
        "tag": "Oconnor"
      }
    ]
  },
  {
    "id": 27,
    "name": "Webster's Furnigeer",
    "price": "$139.16",
    "tags": [
      {
        "id": 0,
        "tag": "Leach"
      },
      {
        "id": 1,
        "tag": "Jillian"
      },
      {
        "id": 2,
        "tag": "Key"
      },
      {
        "id": 3,
        "tag": "Jarvis"
      },
      {
        "id": 4,
        "tag": "Gillespie"
      },
      {
        "id": 5,
        "tag": "Nicholson"
      },
      {
        "id": 6,
        "tag": "Queen"
      },
      {
        "id": 7,
        "tag": "Annie"
      },
      {
        "id": 8,
        "tag": "Hatfield"
      },
      {
        "id": 9,
        "tag": "Michael"
      },
      {
        "id": 10,
        "tag": "Miranda"
      },
      {
        "id": 11,
        "tag": "Goldie"
      }
    ]
  },
  {
    "id": 28,
    "name": "Carney's Isosure",
    "price": "$242.94",
    "tags": [
      {
        "id": 0,
        "tag": "Saundra"
      },
      {
        "id": 1,
        "tag": "Maldonado"
      },
      {
        "id": 2,
        "tag": "Richards"
      },
      {
        "id": 3,
        "tag": "Kerry"
      },
      {
        "id": 4,
        "tag": "Mcleod"
      },
      {
        "id": 5,
        "tag": "Glenn"
      }
    ]
  },
  {
    "id": 29,
    "name": "Hayes's Zillacon",
    "price": "$269.85",
    "tags": [
      {
        "id": 0,
        "tag": "Amy"
      },
      {
        "id": 1,
        "tag": "Rachael"
      },
      {
        "id": 2,
        "tag": "Juanita"
      },
      {
        "id": 3,
        "tag": "Lola"
      },
      {
        "id": 4,
        "tag": "Mcdonald"
      },
      {
        "id": 5,
        "tag": "Shields"
      },
      {
        "id": 6,
        "tag": "Tiffany"
      },
      {
        "id": 7,
        "tag": "Francis"
      }
    ]
  },
  {
    "id": 30,
    "name": "Fulton's Animalia",
    "price": "$383.96",
    "tags": [
      {
        "id": 0,
        "tag": "Burnett"
      },
      {
        "id": 1,
        "tag": "Ava"
      },
      {
        "id": 2,
        "tag": "Marks"
      },
      {
        "id": 3,
        "tag": "Millicent"
      },
      {
        "id": 4,
        "tag": "Graves"
      },
      {
        "id": 5,
        "tag": "Jessie"
      }
    ]
  },
  {
    "id": 31,
    "name": "Francis's Bulljuice",
    "price": "$340.34",
    "tags": [
      {
        "id": 0,
        "tag": "Booth"
      },
      {
        "id": 1,
        "tag": "Chen"
      },
      {
        "id": 2,
        "tag": "Sandoval"
      },
      {
        "id": 3,
        "tag": "Shirley"
      },
      {
        "id": 4,
        "tag": "Blackburn"
      },
      {
        "id": 5,
        "tag": "Walls"
      },
      {
        "id": 6,
        "tag": "Nikki"
      },
      {
        "id": 7,
        "tag": "Maritza"
      },
      {
        "id": 8,
        "tag": "Dionne"
      }
    ]
  },
  {
    "id": 32,
    "name": "Dunn's Imant",
    "price": "$315.38",
    "tags": [
      {
        "id": 0,
        "tag": "Nita"
      },
      {
        "id": 1,
        "tag": "Saunders"
      },
      {
        "id": 2,
        "tag": "Theresa"
      },
      {
        "id": 3,
        "tag": "Duffy"
      },
      {
        "id": 4,
        "tag": "Bradshaw"
      },
      {
        "id": 5,
        "tag": "Pearlie"
      }
    ]
  },
  {
    "id": 33,
    "name": "Burgess's Fortean",
    "price": "$82.67",
    "tags": [
      {
        "id": 0,
        "tag": "Doyle"
      }
    ]
  },
  {
    "id": 34,
    "name": "Wells's Acrodance",
    "price": "$137.79",
    "tags": [
      {
        "id": 0,
        "tag": "Christie"
      }
    ]
  },
  {
    "id": 35,
    "name": "Durham's Bugsall",
    "price": "$293.5",
    "tags": [
      {
        "id": 0,
        "tag": "Lorie"
      },
      {
        "id": 1,
        "tag": "Collins"
      },
      {
        "id": 2,
        "tag": "Singleton"
      },
      {
        "id": 3,
        "tag": "Gertrude"
      },
      {
        "id": 4,
        "tag": "Cecile"
      },
      {
        "id": 5,
        "tag": "Collier"
      },
      {
        "id": 6,
        "tag": "Hunter"
      },
      {
        "id": 7,
        "tag": "Marietta"
      },
      {
        "id": 8,
        "tag": "Gracie"
      },
      {
        "id": 9,
        "tag": "Christensen"
      },
      {
        "id": 10,
        "tag": "May"
      },
      {
        "id": 11,
        "tag": "Brianna"
      }
    ]
  },
  {
    "id": 36,
    "name": "Morrow's Austex",
    "price": "$195.98",
    "tags": [
      {
        "id": 0,
        "tag": "Leila"
      },
      {
        "id": 1,
        "tag": "Waters"
      },
      {
        "id": 2,
        "tag": "Acevedo"
      },
      {
        "id": 3,
        "tag": "Myrtle"
      },
      {
        "id": 4,
        "tag": "Mcclure"
      },
      {
        "id": 5,
        "tag": "Cannon"
      },
      {
        "id": 6,
        "tag": "Beverly"
      },
      {
        "id": 7,
        "tag": "Mcgowan"
      },
      {
        "id": 8,
        "tag": "Stefanie"
      },
      {
        "id": 9,
        "tag": "Lupe"
      }
    ]
  },
  {
    "id": 37,
    "name": "Potter's Comvene",
    "price": "$306.32",
    "tags": [
      {
        "id": 0,
        "tag": "Violet"
      },
      {
        "id": 1,
        "tag": "Savannah"
      },
      {
        "id": 2,
        "tag": "Bobbi"
      },
      {
        "id": 3,
        "tag": "Angela"
      },
      {
        "id": 4,
        "tag": "Lloyd"
      },
      {
        "id": 5,
        "tag": "Carter"
      },
      {
        "id": 6,
        "tag": "Jayne"
      },
      {
        "id": 7,
        "tag": "Lesa"
      },
      {
        "id": 8,
        "tag": "Fuller"
      }
    ]
  },
  {
    "id": 38,
    "name": "Hurst's Squish",
    "price": "$105.64",
    "tags": [
      {
        "id": 0,
        "tag": "Craig"
      },
      {
        "id": 1,
        "tag": "Kay"
      }
    ]
  },
  {
    "id": 39,
    "name": "David's Plasmosis",
    "price": "$366.15",
    "tags": [
      {
        "id": 0,
        "tag": "Olga"
      }
    ]
  },
  {
    "id": 40,
    "name": "Clarke's Liquidoc",
    "price": "$181.52",
    "tags": [
      {
        "id": 0,
        "tag": "Shaw"
      },
      {
        "id": 1,
        "tag": "Hogan"
      },
      {
        "id": 2,
        "tag": "Leigh"
      },
      {
        "id": 3,
        "tag": "Marcy"
      },
      {
        "id": 4,
        "tag": "Sanders"
      },
      {
        "id": 5,
        "tag": "Liza"
      },
      {
        "id": 6,
        "tag": "Underwood"
      },
      {
        "id": 7,
        "tag": "Wood"
      },
      {
        "id": 8,
        "tag": "Griffith"
      },
      {
        "id": 9,
        "tag": "Nadia"
      },
      {
        "id": 10,
        "tag": "Beulah"
      }
    ]
  },
  {
    "id": 41,
    "name": "Travis's Isodrive",
    "price": "$127.2",
    "tags": [
      {
        "id": 0,
        "tag": "Gonzalez"
      },
      {
        "id": 1,
        "tag": "Simone"
      },
      {
        "id": 2,
        "tag": "Nona"
      },
      {
        "id": 3,
        "tag": "Newton"
      },
      {
        "id": 4,
        "tag": "Jeannie"
      },
      {
        "id": 5,
        "tag": "Garcia"
      },
      {
        "id": 6,
        "tag": "Salazar"
      },
      {
        "id": 7,
        "tag": "Lolita"
      },
      {
        "id": 8,
        "tag": "Craft"
      },
      {
        "id": 9,
        "tag": "Farley"
      },
      {
        "id": 10,
        "tag": "Patsy"
      },
      {
        "id": 11,
        "tag": "Pamela"
      }
    ]
  },
  {
    "id": 42,
    "name": "Barry's Polaria",
    "price": "$242.93",
    "tags": [
      {
        "id": 0,
        "tag": "Skinner"
      },
      {
        "id": 1,
        "tag": "Sue"
      },
      {
        "id": 2,
        "tag": "Grace"
      },
      {
        "id": 3,
        "tag": "Sally"
      },
      {
        "id": 4,
        "tag": "Edith"
      },
      {
        "id": 5,
        "tag": "Vance"
      },
      {
        "id": 6,
        "tag": "Barbra"
      }
    ]
  },
  {
    "id": 43,
    "name": "Kinney's Tetratrex",
    "price": "$281.06",
    "tags": [
      {
        "id": 0,
        "tag": "Clark"
      },
      {
        "id": 1,
        "tag": "Webster"
      },
      {
        "id": 2,
        "tag": "Nolan"
      },
      {
        "id": 3,
        "tag": "Burns"
      },
      {
        "id": 4,
        "tag": "Jennie"
      },
      {
        "id": 5,
        "tag": "Webb"
      },
      {
        "id": 6,
        "tag": "Adele"
      },
      {
        "id": 7,
        "tag": "Kathryn"
      },
      {
        "id": 8,
        "tag": "Mayo"
      },
      {
        "id": 9,
        "tag": "Bishop"
      },
      {
        "id": 10,
        "tag": "Hardy"
      }
    ]
  },
  {
    "id": 44,
    "name": "Gray's Marqet",
    "price": "$64.15",
    "tags": [
      {
        "id": 0,
        "tag": "Crane"
      },
      {
        "id": 1,
        "tag": "Jeannette"
      },
      {
        "id": 2,
        "tag": "Mari"
      },
      {
        "id": 3,
        "tag": "Maxwell"
      },
      {
        "id": 4,
        "tag": "Romero"
      },
      {
        "id": 5,
        "tag": "Atkinson"
      },
      {
        "id": 6,
        "tag": "Powers"
      },
      {
        "id": 7,
        "tag": "Zelma"
      },
      {
        "id": 8,
        "tag": "Augusta"
      },
      {
        "id": 9,
        "tag": "Suarez"
      }
    ]
  },
  {
    "id": 45,
    "name": "Hutchinson's Quizka",
    "price": "$4.93",
    "tags": [
      {
        "id": 0,
        "tag": "Tracey"
      },
      {
        "id": 1,
        "tag": "Rhoda"
      },
      {
        "id": 2,
        "tag": "Manning"
      },
      {
        "id": 3,
        "tag": "Lesley"
      },
      {
        "id": 4,
        "tag": "Leona"
      },
      {
        "id": 5,
        "tag": "Nichols"
      },
      {
        "id": 6,
        "tag": "Deanne"
      },
      {
        "id": 7,
        "tag": "Estes"
      },
      {
        "id": 8,
        "tag": "Russell"
      },
      {
        "id": 9,
        "tag": "Kimberly"
      },
      {
        "id": 10,
        "tag": "Ernestine"
      },
      {
        "id": 11,
        "tag": "Kristine"
      }
    ]
  },
  {
    "id": 46,
    "name": "Mcguire's Liquicom",
    "price": "$389.53",
    "tags": [
      {
        "id": 0,
        "tag": "Mendoza"
      },
      {
        "id": 1,
        "tag": "Mathews"
      },
      {
        "id": 2,
        "tag": "Kathrine"
      },
      {
        "id": 3,
        "tag": "Jensen"
      },
      {
        "id": 4,
        "tag": "Harriett"
      },
      {
        "id": 5,
        "tag": "Heidi"
      }
    ]
  },
  {
    "id": 47,
    "name": "Wyatt's Exoteric",
    "price": "$88.44",
    "tags": [
      {
        "id": 0,
        "tag": "Carson"
      },
      {
        "id": 1,
        "tag": "Delaney"
      },
      {
        "id": 2,
        "tag": "Castaneda"
      },
      {
        "id": 3,
        "tag": "Lopez"
      },
      {
        "id": 4,
        "tag": "Dena"
      }
    ]
  },
  {
    "id": 48,
    "name": "Garner's Orboid",
    "price": "$236.32",
    "tags": [
      {
        "id": 0,
        "tag": "Anastasia"
      },
      {
        "id": 1,
        "tag": "Jordan"
      },
      {
        "id": 2,
        "tag": "Mccray"
      },
      {
        "id": 3,
        "tag": "Sexton"
      },
      {
        "id": 4,
        "tag": "Winifred"
      },
      {
        "id": 5,
        "tag": "Carmela"
      },
      {
        "id": 6,
        "tag": "Rosario"
      }
    ]
  },
  {
    "id": 49,
    "name": "Knight's Ozean",
    "price": "$377.42",
    "tags": [
      {
        "id": 0,
        "tag": "Sanchez"
      },
      {
        "id": 1,
        "tag": "Abby"
      },
      {
        "id": 2,
        "tag": "Aline"
      },
      {
        "id": 3,
        "tag": "Tonya"
      },
      {
        "id": 4,
        "tag": "Good"
      }
    ]
  },
  {
    "id": 50,
    "name": "Dean's Emoltra",
    "price": "$196.71",
    "tags": [
      {
        "id": 0,
        "tag": "Henderson"
      }
    ]
  },
  {
    "id": 51,
    "name": "Carroll's Soprano",
    "price": "$35.5",
    "tags": [
      {
        "id": 0,
        "tag": "Luz"
      }
    ]
  },
  {
    "id": 52,
    "name": "Conway's Zytrax",
    "price": "$385.17",
    "tags": [
      {
        "id": 0,
        "tag": "Lavonne"
      },
      {
        "id": 1,
        "tag": "Beatrice"
      },
      {
        "id": 2,
        "tag": "Shana"
      },
      {
        "id": 3,
        "tag": "Tommie"
      },
      {
        "id": 4,
        "tag": "Schultz"
      },
      {
        "id": 5,
        "tag": "Parsons"
      },
      {
        "id": 6,
        "tag": "Grimes"
      },
      {
        "id": 7,
        "tag": "Solomon"
      }
    ]
  },
  {
    "id": 53,
    "name": "Hartman's Emergent",
    "price": "$88.09",
    "tags": [
      {
        "id": 0,
        "tag": "Howell"
      },
      {
        "id": 1,
        "tag": "Cunningham"
      },
      {
        "id": 2,
        "tag": "Ebony"
      },
      {
        "id": 3,
        "tag": "Lamb"
      },
      {
        "id": 4,
        "tag": "Nash"
      },
      {
        "id": 5,
        "tag": "Marquita"
      },
      {
        "id": 6,
        "tag": "Courtney"
      },
      {
        "id": 7,
        "tag": "Louise"
      }
    ]
  },
  {
    "id": 54,
    "name": "Rocha's Isoplex",
    "price": "$256.03",
    "tags": [
      {
        "id": 0,
        "tag": "Petty"
      },
      {
        "id": 1,
        "tag": "Deloris"
      },
      {
        "id": 2,
        "tag": "Roberta"
      },
      {
        "id": 3,
        "tag": "Malone"
      },
      {
        "id": 4,
        "tag": "Bass"
      },
      {
        "id": 5,
        "tag": "Brenda"
      }
    ]
  },
  {
    "id": 55,
    "name": "Henderson's Enaut",
    "price": "$35.92",
    "tags": [
      {
        "id": 0,
        "tag": "Hattie"
      },
      {
        "id": 1,
        "tag": "Daugherty"
      },
      {
        "id": 2,
        "tag": "Cotton"
      },
      {
        "id": 3,
        "tag": "Roth"
      },
      {
        "id": 4,
        "tag": "Wolf"
      },
      {
        "id": 5,
        "tag": "Harrison"
      }
    ]
  },
  {
    "id": 56,
    "name": "Houston's Entropix",
    "price": "$168.11",
    "tags": [
      {
        "id": 0,
        "tag": "Willa"
      },
      {
        "id": 1,
        "tag": "Carla"
      },
      {
        "id": 2,
        "tag": "Hollie"
      },
      {
        "id": 3,
        "tag": "Karyn"
      }
    ]
  },
  {
    "id": 57,
    "name": "Rodriquez's Virva",
    "price": "$209.63",
    "tags": [
      {
        "id": 0,
        "tag": "Nora"
      },
      {
        "id": 1,
        "tag": "Ines"
      },
      {
        "id": 2,
        "tag": "Tasha"
      }
    ]
  },
  {
    "id": 58,
    "name": "Callahan's Architax",
    "price": "$375.9",
    "tags": [
      {
        "id": 0,
        "tag": "Mcbride"
      },
      {
        "id": 1,
        "tag": "Helga"
      },
      {
        "id": 2,
        "tag": "Debra"
      },
      {
        "id": 3,
        "tag": "Duncan"
      },
      {
        "id": 4,
        "tag": "Barbara"
      },
      {
        "id": 5,
        "tag": "Stacey"
      },
      {
        "id": 6,
        "tag": "Oneil"
      },
      {
        "id": 7,
        "tag": "Geneva"
      },
      {
        "id": 8,
        "tag": "Genevieve"
      },
      {
        "id": 9,
        "tag": "Andrea"
      }
    ]
  },
  {
    "id": 59,
    "name": "Bell's Zaggle",
    "price": "$367.7",
    "tags": [
      {
        "id": 0,
        "tag": "Candy"
      }
    ]
  },
  {
    "id": 60,
    "name": "Snow's Grupoli",
    "price": "$320.64",
    "tags": [
      {
        "id": 0,
        "tag": "Jodie"
      },
      {
        "id": 1,
        "tag": "Stark"
      },
      {
        "id": 2,
        "tag": "Emma"
      }
    ]
  },
  {
    "id": 61,
    "name": "Woodward's Essensia",
    "price": "$385.15",
    "tags": [
      {
        "id": 0,
        "tag": "Kellie"
      }
    ]
  },
  {
    "id": 62,
    "name": "Brewer's Oatfarm",
    "price": "$177.8",
    "tags": [
      {
        "id": 0,
        "tag": "Johanna"
      },
      {
        "id": 1,
        "tag": "Deanna"
      },
      {
        "id": 2,
        "tag": "Young"
      },
      {
        "id": 3,
        "tag": "Wanda"
      },
      {
        "id": 4,
        "tag": "Jenna"
      }
    ]
  },
  {
    "id": 63,
    "name": "Reid's Comtours",
    "price": "$149.88",
    "tags": [
      {
        "id": 0,
        "tag": "Natasha"
      },
      {
        "id": 1,
        "tag": "Wall"
      },
      {
        "id": 2,
        "tag": "Becky"
      },
      {
        "id": 3,
        "tag": "Matilda"
      },
      {
        "id": 4,
        "tag": "Eloise"
      },
      {
        "id": 5,
        "tag": "Joseph"
      },
      {
        "id": 6,
        "tag": "Georgina"
      },
      {
        "id": 7,
        "tag": "Drake"
      },
      {
        "id": 8,
        "tag": "Hayden"
      },
      {
        "id": 9,
        "tag": "Randolph"
      },
      {
        "id": 10,
        "tag": "Wilda"
      },
      {
        "id": 11,
        "tag": "Mcpherson"
      }
    ]
  },
  {
    "id": 64,
    "name": "Gould's Cognicode",
    "price": "$139.98",
    "tags": [
      {
        "id": 0,
        "tag": "Ethel"
      },
      {
        "id": 1,
        "tag": "Wilkinson"
      },
      {
        "id": 2,
        "tag": "Ester"
      },
      {
        "id": 3,
        "tag": "Scott"
      },
      {
        "id": 4,
        "tag": "Gaines"
      },
      {
        "id": 5,
        "tag": "Molina"
      },
      {
        "id": 6,
        "tag": "Erma"
      },
      {
        "id": 7,
        "tag": "Mitchell"
      },
      {
        "id": 8,
        "tag": "Bond"
      }
    ]
  },
  {
    "id": 65,
    "name": "English's Mantro",
    "price": "$183.93",
    "tags": [
      {
        "id": 0,
        "tag": "Ray"
      }
    ]
  },
  {
    "id": 66,
    "name": "Melton's Kyagoro",
    "price": "$239.17",
    "tags": [
      {
        "id": 0,
        "tag": "Rene"
      },
      {
        "id": 1,
        "tag": "Tracy"
      },
      {
        "id": 2,
        "tag": "Leanna"
      },
      {
        "id": 3,
        "tag": "Belinda"
      },
      {
        "id": 4,
        "tag": "Monroe"
      },
      {
        "id": 5,
        "tag": "Elma"
      },
      {
        "id": 6,
        "tag": "Buchanan"
      },
      {
        "id": 7,
        "tag": "Casey"
      }
    ]
  },
  {
    "id": 67,
    "name": "Floyd's Olympix",
    "price": "$392.43",
    "tags": [
      {
        "id": 0,
        "tag": "Bowen"
      },
      {
        "id": 1,
        "tag": "Karin"
      },
      {
        "id": 2,
        "tag": "Bianca"
      },
      {
        "id": 3,
        "tag": "Ellison"
      }
    ]
  },
  {
    "id": 68,
    "name": "Wilson's Chillium",
    "price": "$254.6",
    "tags": [
      {
        "id": 0,
        "tag": "Tameka"
      },
      {
        "id": 1,
        "tag": "Robbie"
      },
      {
        "id": 2,
        "tag": "Althea"
      },
      {
        "id": 3,
        "tag": "Albert"
      },
      {
        "id": 4,
        "tag": "Blair"
      },
      {
        "id": 5,
        "tag": "Alexandria"
      },
      {
        "id": 6,
        "tag": "Eleanor"
      },
      {
        "id": 7,
        "tag": "Wong"
      }
    ]
  },
  {
    "id": 69,
    "name": "Trevino's Ecratic",
    "price": "$187.28",
    "tags": [
      {
        "id": 0,
        "tag": "Kirkland"
      },
      {
        "id": 1,
        "tag": "Jerri"
      },
      {
        "id": 2,
        "tag": "Lizzie"
      },
      {
        "id": 3,
        "tag": "Obrien"
      },
      {
        "id": 4,
        "tag": "Sweeney"
      },
      {
        "id": 5,
        "tag": "Fowler"
      }
    ]
  },
  {
    "id": 70,
    "name": "Luna's Cujo",
    "price": "$334",
    "tags": [
      {
        "id": 0,
        "tag": "Cathleen"
      },
      {
        "id": 1,
        "tag": "Stephens"
      },
      {
        "id": 2,
        "tag": "Puckett"
      },
      {
        "id": 3,
        "tag": "Hammond"
      },
      {
        "id": 4,
        "tag": "Hubbard"
      }
    ]
  },
  {
    "id": 71,
    "name": "Acevedo's Kog",
    "price": "$78.03",
    "tags": [
      {
        "id": 0,
        "tag": "Kent"
      },
      {
        "id": 1,
        "tag": "Meyers"
      }
    ]
  },
  {
    "id": 72,
    "name": "Lucas's Zentry",
    "price": "$45.33",
    "tags": [
      {
        "id": 0,
        "tag": "Lacy"
      },
      {
        "id": 1,
        "tag": "Rosetta"
      }
    ]
  },
  {
    "id": 73,
    "name": "Oneill's Quailcom",
    "price": "$378.38",
    "tags": [
      {
        "id": 0,
        "tag": "Marianne"
      },
      {
        "id": 1,
        "tag": "Elisa"
      },
      {
        "id": 2,
        "tag": "Jeannine"
      },
      {
        "id": 3,
        "tag": "Gay"
      },
      {
        "id": 4,
        "tag": "Maude"
      },
      {
        "id": 5,
        "tag": "Perez"
      },
      {
        "id": 6,
        "tag": "Blanche"
      },
      {
        "id": 7,
        "tag": "Aileen"
      },
      {
        "id": 8,
        "tag": "Bridget"
      },
      {
        "id": 9,
        "tag": "Louisa"
      },
      {
        "id": 10,
        "tag": "Hester"
      }
    ]
  },
  {
    "id": 74,
    "name": "Logan's Satiance",
    "price": "$345.4",
    "tags": [
      {
        "id": 0,
        "tag": "Lucile"
      },
      {
        "id": 1,
        "tag": "Lori"
      },
      {
        "id": 2,
        "tag": "Darcy"
      }
    ]
  },
  {
    "id": 75,
    "name": "Combs's Skyplex",
    "price": "$302.25",
    "tags": [
      {
        "id": 0,
        "tag": "Marquez"
      },
      {
        "id": 1,
        "tag": "Odom"
      }
    ]
  },
  {
    "id": 76,
    "name": "Swanson's Aquasseur",
    "price": "$183.77",
    "tags": [
      {
        "id": 0,
        "tag": "Pollard"
      },
      {
        "id": 1,
        "tag": "Evelyn"
      },
      {
        "id": 2,
        "tag": "Alvarez"
      }
    ]
  },
  {
    "id": 77,
    "name": "Fry's Hometown",
    "price": "$124.02",
    "tags": [
      {
        "id": 0,
        "tag": "Jody"
      },
      {
        "id": 1,
        "tag": "Marta"
      },
      {
        "id": 2,
        "tag": "Marva"
      },
      {
        "id": 3,
        "tag": "Thomas"
      },
      {
        "id": 4,
        "tag": "Wells"
      },
      {
        "id": 5,
        "tag": "Lakeisha"
      },
      {
        "id": 6,
        "tag": "Spears"
      },
      {
        "id": 7,
        "tag": "Sims"
      },
      {
        "id": 8,
        "tag": "Adeline"
      },
      {
        "id": 9,
        "tag": "Marisa"
      }
    ]
  },
  {
    "id": 78,
    "name": "Pittman's Cemention",
    "price": "$44.35",
    "tags": [
      {
        "id": 0,
        "tag": "Rita"
      }
    ]
  },
  {
    "id": 79,
    "name": "Serrano's Eargo",
    "price": "$137.61",
    "tags": [
      {
        "id": 0,
        "tag": "Sears"
      },
      {
        "id": 1,
        "tag": "Leonor"
      },
      {
        "id": 2,
        "tag": "Mason"
      },
      {
        "id": 3,
        "tag": "Suzette"
      },
      {
        "id": 4,
        "tag": "Petersen"
      },
      {
        "id": 5,
        "tag": "Lester"
      },
      {
        "id": 6,
        "tag": "Mollie"
      },
      {
        "id": 7,
        "tag": "Valdez"
      },
      {
        "id": 8,
        "tag": "Frazier"
      },
      {
        "id": 9,
        "tag": "Tran"
      },
      {
        "id": 10,
        "tag": "Compton"
      }
    ]
  },
  {
    "id": 80,
    "name": "Randall's Kage",
    "price": "$115.6",
    "tags": [
      {
        "id": 0,
        "tag": "Workman"
      },
      {
        "id": 1,
        "tag": "Michele"
      },
      {
        "id": 2,
        "tag": "Phillips"
      },
      {
        "id": 3,
        "tag": "Ferguson"
      },
      {
        "id": 4,
        "tag": "Ruby"
      },
      {
        "id": 5,
        "tag": "Serena"
      }
    ]
  },
  {
    "id": 81,
    "name": "Sutton's Nitracyr",
    "price": "$369.98",
    "tags": [
      {
        "id": 0,
        "tag": "Davis"
      },
      {
        "id": 1,
        "tag": "Erickson"
      },
      {
        "id": 2,
        "tag": "Nola"
      },
      {
        "id": 3,
        "tag": "Claudine"
      },
      {
        "id": 4,
        "tag": "Concepcion"
      }
    ]
  },
  {
    "id": 82,
    "name": "Downs's Quilk",
    "price": "$126.04",
    "tags": [
      {
        "id": 0,
        "tag": "Rosalie"
      },
      {
        "id": 1,
        "tag": "Alexis"
      },
      {
        "id": 2,
        "tag": "Shawna"
      },
      {
        "id": 3,
        "tag": "Shaffer"
      },
      {
        "id": 4,
        "tag": "Keith"
      },
      {
        "id": 5,
        "tag": "Valencia"
      },
      {
        "id": 6,
        "tag": "Terra"
      },
      {
        "id": 7,
        "tag": "Berta"
      },
      {
        "id": 8,
        "tag": "Constance"
      },
      {
        "id": 9,
        "tag": "Alyce"
      }
    ]
  },
  {
    "id": 83,
    "name": "Schneider's Emtrak",
    "price": "$263.3",
    "tags": [
      {
        "id": 0,
        "tag": "Wallace"
      },
      {
        "id": 1,
        "tag": "Jessica"
      },
      {
        "id": 2,
        "tag": "Lee"
      },
      {
        "id": 3,
        "tag": "Vilma"
      }
    ]
  },
  {
    "id": 84,
    "name": "Le's Kidgrease",
    "price": "$130.89",
    "tags": [
      {
        "id": 0,
        "tag": "Caitlin"
      },
      {
        "id": 1,
        "tag": "Dawson"
      },
      {
        "id": 2,
        "tag": "Molly"
      },
      {
        "id": 3,
        "tag": "Wagner"
      },
      {
        "id": 4,
        "tag": "Gilmore"
      },
      {
        "id": 5,
        "tag": "Knight"
      },
      {
        "id": 6,
        "tag": "Tara"
      },
      {
        "id": 7,
        "tag": "Flossie"
      },
      {
        "id": 8,
        "tag": "Joyce"
      },
      {
        "id": 9,
        "tag": "Luann"
      },
      {
        "id": 10,
        "tag": "Knapp"
      },
      {
        "id": 11,
        "tag": "Shanna"
      }
    ]
  },
  {
    "id": 85,
    "name": "Decker's Xixan",
    "price": "$150.19",
    "tags": [
      {
        "id": 0,
        "tag": "Addie"
      },
      {
        "id": 1,
        "tag": "Aguirre"
      },
      {
        "id": 2,
        "tag": "Trina"
      },
      {
        "id": 3,
        "tag": "Teresa"
      },
      {
        "id": 4,
        "tag": "Krystal"
      },
      {
        "id": 5,
        "tag": "Roach"
      },
      {
        "id": 6,
        "tag": "Calderon"
      },
      {
        "id": 7,
        "tag": "Nina"
      },
      {
        "id": 8,
        "tag": "Mcguire"
      },
      {
        "id": 9,
        "tag": "Chase"
      },
      {
        "id": 10,
        "tag": "Mitzi"
      },
      {
        "id": 11,
        "tag": "Ofelia"
      }
    ]
  },
  {
    "id": 86,
    "name": "Duran's Cubix",
    "price": "$230.61",
    "tags": [
      {
        "id": 0,
        "tag": "Olivia"
      }
    ]
  },
  {
    "id": 87,
    "name": "Fisher's Xanide",
    "price": "$187.62",
    "tags": [
      {
        "id": 0,
        "tag": "Zamora"
      },
      {
        "id": 1,
        "tag": "Lindsay"
      },
      {
        "id": 2,
        "tag": "Helena"
      },
      {
        "id": 3,
        "tag": "Patterson"
      },
      {
        "id": 4,
        "tag": "Mosley"
      },
      {
        "id": 5,
        "tag": "Vargas"
      },
      {
        "id": 6,
        "tag": "Dina"
      },
      {
        "id": 7,
        "tag": "Sheppard"
      },
      {
        "id": 8,
        "tag": "Pearson"
      },
      {
        "id": 9,
        "tag": "Carroll"
      },
      {
        "id": 10,
        "tag": "Evans"
      }
    ]
  },
  {
    "id": 88,
    "name": "Hatfield's Geekmosis",
    "price": "$166.56",
    "tags": [
      {
        "id": 0,
        "tag": "Isabelle"
      }
    ]
  },
  {
    "id": 89,
    "name": "Munoz's Decratex",
    "price": "$74.87",
    "tags": [
      {
        "id": 0,
        "tag": "Aurora"
      },
      {
        "id": 1,
        "tag": "Amanda"
      }
    ]
  },
  {
    "id": 90,
    "name": "Mcfarland's Amril",
    "price": "$337.48",
    "tags": [
      {
        "id": 0,
        "tag": "Claire"
      },
      {
        "id": 1,
        "tag": "Wilson"
      },
      {
        "id": 2,
        "tag": "Owens"
      },
      {
        "id": 3,
        "tag": "Davidson"
      },
      {
        "id": 4,
        "tag": "Pickett"
      },
      {
        "id": 5,
        "tag": "Kerri"
      },
      {
        "id": 6,
        "tag": "Lilly"
      },
      {
        "id": 7,
        "tag": "Meghan"
      },
      {
        "id": 8,
        "tag": "Cardenas"
      },
      {
        "id": 9,
        "tag": "Alford"
      },
      {
        "id": 10,
        "tag": "Evangelina"
      },
      {
        "id": 11,
        "tag": "Alisa"
      }
    ]
  },
  {
    "id": 91,
    "name": "Battle's Caxt",
    "price": "$116.72",
    "tags": [
      {
        "id": 0,
        "tag": "Robin"
      },
      {
        "id": 1,
        "tag": "Marshall"
      },
      {
        "id": 2,
        "tag": "Jeri"
      },
      {
        "id": 3,
        "tag": "Horne"
      },
      {
        "id": 4,
        "tag": "Christian"
      },
      {
        "id": 5,
        "tag": "Lynnette"
      },
      {
        "id": 6,
        "tag": "Edwards"
      },
      {
        "id": 7,
        "tag": "Lilian"
      },
      {
        "id": 8,
        "tag": "Patty"
      },
      {
        "id": 9,
        "tag": "Edwina"
      }
    ]
  },
  {
    "id": 92,
    "name": "Holder's Biohab",
    "price": "$241.14",
    "tags": [
      {
        "id": 0,
        "tag": "Wiggins"
      },
      {
        "id": 1,
        "tag": "Miller"
      },
      {
        "id": 2,
        "tag": "Lana"
      },
      {
        "id": 3,
        "tag": "Margo"
      },
      {
        "id": 4,
        "tag": "Fern"
      },
      {
        "id": 5,
        "tag": "Dorthy"
      },
      {
        "id": 6,
        "tag": "Madeleine"
      },
      {
        "id": 7,
        "tag": "Shannon"
      },
      {
        "id": 8,
        "tag": "Bowers"
      },
      {
        "id": 9,
        "tag": "Golden"
      }
    ]
  },
  {
    "id": 93,
    "name": "Holloway's Medifax",
    "price": "$324.21",
    "tags": [
      {
        "id": 0,
        "tag": "Johnston"
      }
    ]
  },
  {
    "id": 94,
    "name": "Dorsey's Bullzone",
    "price": "$127.21",
    "tags": [
      {
        "id": 0,
        "tag": "Debora"
      },
      {
        "id": 1,
        "tag": "Aida"
      },
      {
        "id": 2,
        "tag": "Mendez"
      },
      {
        "id": 3,
        "tag": "Velazquez"
      },
      {
        "id": 4,
        "tag": "Miriam"
      },
      {
        "id": 5,
        "tag": "Lorene"
      },
      {
        "id": 6,
        "tag": "Ramona"
      }
    ]
  },
  {
    "id": 95,
    "name": "Mckay's Exospace",
    "price": "$68.84",
    "tags": [
      {
        "id": 0,
        "tag": "Higgins"
      },
      {
        "id": 1,
        "tag": "Reyna"
      }
    ]
  },
  {
    "id": 96,
    "name": "Wade's Junipoor",
    "price": "$145.16",
    "tags": [
      {
        "id": 0,
        "tag": "Hancock"
      },
      {
        "id": 1,
        "tag": "Gamble"
      },
      {
        "id": 2,
        "tag": "Jennings"
      }
    ]
  },
  {
    "id": 97,
    "name": "Mendoza's Xelegyl",
    "price": "$368.53",
    "tags": [
      {
        "id": 0,
        "tag": "Cecilia"
      },
      {
        "id": 1,
        "tag": "Langley"
      },
      {
        "id": 2,
        "tag": "Macdonald"
      },
      {
        "id": 3,
        "tag": "Juarez"
      }
    ]
  },
  {
    "id": 98,
    "name": "Goodwin's Brainclip",
    "price": "$211.48",
    "tags": [
      {
        "id": 0,
        "tag": "Williamson"
      },
      {
        "id": 1,
        "tag": "Eliza"
      },
      {
        "id": 2,
        "tag": "Lilia"
      },
      {
        "id": 3,
        "tag": "Melanie"
      }
    ]
  },
  {
    "id": 99,
    "name": "Huffman's Xeronk",
    "price": "$391.76",
    "tags": [
      {
        "id": 0,
        "tag": "Dalton"
      },
      {
        "id": 1,
        "tag": "Marcella"
      },
      {
        "id": 2,
        "tag": "Hull"
      },
      {
        "id": 3,
        "tag": "Leslie"
      },
      {
        "id": 4,
        "tag": "Daniel"
      },
      {
        "id": 5,
        "tag": "Green"
      },
      {
        "id": 6,
        "tag": "Osborne"
      }
    ]
  }
]
